{
  "VolatilitySystem": {
    "enabled": true,
    "module": "strategies.volatility_system",
    "class_name": "VolatilitySystem",
    "timeframe": "1h",
    "lookback_hours": 66
  },
  "OTTStrategy": {
    "enabled": true,
    "module": "strategies.ott_strategy",
    "class_name": "OTTStrategy",
    "timeframe": "1h",
    "lookback_hours": 50
  },
  "SupertrendStrategy": {
    "enabled": true,
    "module": "strategies.supertrend_strategy",
    "class_name": "SupertrendStrategy",
    "timeframe": "1h",
    "lookback_hours": 124
  },
  "SpecialKStrategy": {
    "enabled": true,
    "module": "strategies.special_k_strategy",
    "class_name": "SpecialKStrategy",
    "timeframe": "1D",
    "lookback_hours": 19776
  },
  "KamaTrendStrategy": {
    "enabled": true,
    "module": "strategies.kama_trend_strategy",
    "class_name": "KamaTrendStrategy",
    "timeframe": "1h",
    "lookback_hours": 100
  },
  "NewTottStrategy": {
    "enabled": true,
    "module": "strategies.new_tott_strategy",
    "class_name": "NewTottStrategy",
    "timeframe": "15m",
    "lookback_hours": 13
  },
  "RudyBreakoutMomentumV2Strategy": {
    "enabled": true,
    "module": "strategies.rudy_breakout_momentum_v2_strategy",
    "class_name": "RudyBreakoutMomentumV2Strategy",
    "timeframe": "1D",
    "lookback_hours": 3024
  },
  "BjorgumDoubleTapStrategy": {
    "enabled": true,
    "module": "strategies.bjorgum_double_tap_strategy",
    "class_name": "BjorgumDoubleTapStrategy",
    "timeframe": "4h",
    "lookback_hours": null
  }
}
